iit_rehab/__init__.py
iit_rehab/adaptive_oscillator.py
iit_rehab/base_classes.py
iit_rehab/controller.py
iit_rehab/definitions.py
iit_rehab/parser_utils.py
iit_rehab/plot_utils.py
iit_rehab/time_utils.py
iit_rehab-0.0.2.dist-info/METADATA
iit_rehab-0.0.2.dist-info/WHEEL
iit_rehab-0.0.2.dist-info/RECORD
