Metadata-Version: 2.3
Name: iit-rehab
Version: 0.0.2
Summary: Collaboration between IIT and Aries Lab
Author: Tony Smoragiewicz
Author-email: tony.smoragiewicz@tum.de
Requires-Python: >3.12,<4.0
Classifier: Programming Language :: Python :: 3
Classifier: Programming Language :: Python :: 3.13
Requires-Dist: dash (>=3.1.1,<4.0.0)
Requires-Dist: loguru (>=0.7.3,<0.8.0)
Requires-Dist: matplotlib (>=3.10.3,<4.0.0)
Requires-Dist: numpy (>=2.2.3,<3.0.0)
Requires-Dist: pandas (>=2.3.0,<3.0.0)
Requires-Dist: plotly (>=6.2.0,<7.0.0)
Requires-Dist: poetry-core (>=2.1.2,<3.0.0)
Requires-Dist: pre-commit (>=4.1.0,<5.0.0)
Requires-Dist: pytest (>=8.3.5,<9.0.0)
Requires-Dist: pytest-cov (>=6.0.0,<7.0.0)
Requires-Dist: scipy (>=1.15.3,<2.0.0)
Project-URL: homepage, https://github.com/TUM-Aries-Lab/iit_collab
